llmcode_install/__init__.py
llmcode_install/main.py
llmcode_install-0.0.1.dist-info/LICENSE.txt
llmcode_install-0.0.1.dist-info/METADATA
llmcode_install-0.0.1.dist-info/WHEEL
llmcode_install-0.0.1.dist-info/entry_points.txt
llmcode_install-0.0.1.dist-info/top_level.txt
llmcode_install-0.0.1.dist-info/RECORD
