Metadata-Version: 2.1
Name: llmcode-install
Version: 0.0.1
Summary: Installer for the llmcode AI pair programming CLI tool.
Home-page: https://github.com/KhulnaSoft/llmcode
Author: Md Sulaiman
Author-email: dev.sulaiman@icloud.com
Classifier: Programming Language :: Python :: 3
Classifier: License :: OSI Approved :: MIT License
Classifier: Operating System :: OS Independent
Requires-Python: >=3.8
License-File: LICENSE.txt
Requires-Dist: uv >=0.5.0
